{
  "appPageId" : "1baa3c74-f303-4b33-ac8f-b0ea6f4b0d56",
  "componentName" : "siteforce:sldsOneColLayout",
  "dataProviders" : [ ],
  "id" : "95078c99-a9c0-418d-955d-b4d26024a4d8",
  "label" : "Action Plan List",
  "regions" : [ {
    "id" : "1d2f476a-074b-4c74-b1e3-7cc72a27ab9e",
    "regionName" : "header",
    "type" : "region"
  }, {
    "components" : [ {
      "componentAttributes" : {
        "enableInlineEdit" : true,
        "filterName" : "{!filterId}",
        "layout" : "FULL",
        "pageSize" : 25,
        "scope" : "{!objectName}",
        "showActionBar" : true,
        "showChartsPanel" : true,
        "showDisplay" : "showall",
        "showFilterPanel" : true,
        "showImageIcon" : true,
        "showManualRefreshButton" : true,
        "showObjectName" : true,
        "showPinnedList" : true,
        "showSearchBar" : true
      },
      "componentName" : "forceCommunity:objectHome",
      "id" : "d52db243-497d-4928-a60b-62d5a5ffe597",
      "renderPriority" : "NEUTRAL",
      "renditionMap" : { },
      "type" : "component"
    } ],
    "id" : "c78170a6-62de-415d-a18f-8007f3d69860",
    "regionName" : "content",
    "type" : "region"
  }, {
    "id" : "83bebbc2-2638-461b-828c-1efe91b5b3ca",
    "regionName" : "footer",
    "type" : "region"
  } ],
  "themeLayoutType" : "Inner",
  "type" : "view",
  "viewType" : "list-07r"
}