{
  "appPageId" : "375e973f-7bf4-40bf-971d-e9adf9361e1c",
  "componentName" : "siteforce:sldsOneColLayout",
  "dataProviders" : [ ],
  "id" : "901d489d-9a25-4513-b15c-c1a2d9fe81a5",
  "label" : "Forgot Password",
  "regions" : [ {
    "components" : [ {
      "componentAttributes" : {
        "richTextValue" : "<div style=\"text-align: center;\"><span class=\"inverseTextColor\" style=\"font-size:22px\">PASSWORD RESET</span></div>"
      },
      "componentName" : "forceCommunity:richTextInline",
      "id" : "62093778-cc39-4455-83ed-cfb0337a48af",
      "renderPriority" : "NEUTRAL",
      "renditionMap" : { },
      "type" : "component"
    }, {
      "componentAttributes" : {
        "richTextValue" : "<div class=\"inverseTextColor\" style=\"text-align: center;\">To reset your password, we'll need your username.<br/> We'll send password reset instructions to the email address associated with your account.</div>"
      },
      "componentName" : "forceCommunity:richTextInline",
      "id" : "e2d8b712-c1a3-4e69-a48a-0c5cfb320c1b",
      "renderPriority" : "NEUTRAL",
      "renditionMap" : { },
      "type" : "component"
    }, {
      "componentAttributes" : {
        "checkEmailUrl" : "./CheckPasswordResetEmail",
        "submitButtonLabel" : "Reset Password",
        "usernameLabel" : "Username"
      },
      "componentName" : "salesforceIdentity:forgotPassword2",
      "id" : "9011f831-d373-47b3-8557-e1480e48bfca",
      "renderPriority" : "NEUTRAL",
      "renditionMap" : { },
      "type" : "component"
    }, {
      "componentAttributes" : {
        "richTextValue" : "<div style=\"text-align: center;\"><a class=\"inverseTextColor\" href=\"./\">Cancel</a></div>"
      },
      "componentName" : "forceCommunity:richTextInline",
      "id" : "603e0a7b-a221-428f-b70e-8d66ccc5f8bb",
      "renderPriority" : "NEUTRAL",
      "renditionMap" : { },
      "type" : "component"
    } ],
    "id" : "805935e4-70d0-450d-8416-fe32f6bf4b92",
    "regionName" : "content",
    "type" : "region"
  }, {
    "components" : [ {
      "componentAttributes" : {
        "customHeadTags" : "",
        "description" : "",
        "title" : "Forgot Password"
      },
      "componentName" : "forceCommunity:seoAssistant",
      "id" : "30b3fd4d-1eac-4d2f-921c-9dac54d3f693",
      "renditionMap" : { },
      "type" : "component"
    } ],
    "id" : "98d85e7a-485e-4302-9996-7f88c2917e54",
    "regionName" : "sfdcHiddenRegion",
    "type" : "region"
  } ],
  "themeLayoutType" : "Login",
  "type" : "view",
  "viewType" : "forgot-password"
}