{
  "appPageId" : "1baa3c74-f303-4b33-ac8f-b0ea6f4b0d56",
  "componentName" : "siteforce:sldsTwoCol84Layout",
  "dataProviders" : [ ],
  "id" : "fc88a044-4149-4207-a64a-bde76ce92770",
  "label" : "Home",
  "regions" : [ {
    "components" : [ {
      "componentAttributes" : {
        "richTextValue" : "<img class='sfdcCbImage' src='/sfsites/c/img/community/cpt/cpt-home-banner.png'             style='width:100%;'/>"
      },
      "componentName" : "forceCommunity:richTextInline",
      "id" : "dc676c48-1d4c-44fb-bce9-8625ef484851",
      "renderPriority" : "NEUTRAL",
      "renditionMap" : { },
      "type" : "component"
    }, {
      "componentAttributes" : {
        "bannerBackgroundColor" : "",
        "bannerPosition" : "top",
        "bannerSizePercent" : 35,
        "borderRadius" : 20,
        "boxShadow" : true,
        "haveBanner" : false,
        "iconBackgroundColor" : "rgb(255,255,255)",
        "iconSize" : "medium",
        "noImageColor" : "rgb(116,116,116)",
        "overlay" : "rgba(0,0,0,0.01)",
        "templateType" : "default",
        "titleColor" : "",
        "titleFontSize" : "medium",
        "titleHorizontalAlign" : "center"
      },
      "componentName" : "community_navigation:tileMenu",
      "id" : "fa06ebb4-d704-4e82-b6bc-841a93df1467",
      "renderPriority" : "NEUTRAL",
      "renditionMap" : { },
      "type" : "component"
    } ],
    "id" : "ccc133ff-4e76-43f3-8a6f-fce7e13c4d8b",
    "regionName" : "header",
    "type" : "region"
  }, {
    "components" : [ {
      "componentAttributes" : {
        "enableInlineEdit" : true,
        "filterName" : "MyOpenCases",
        "layout" : "STANDARD",
        "pageSize" : 5,
        "scope" : "Case",
        "showActionBar" : true,
        "showChartsPanel" : true,
        "showDisplay" : "showall",
        "showFilterPanel" : true,
        "showImageIcon" : true,
        "showManualRefreshButton" : true,
        "showObjectName" : true,
        "showPinnedList" : true,
        "showSearchBar" : true
      },
      "componentName" : "forceCommunity:objectHome",
      "id" : "ad040314-923c-4bc2-9954-3765d7b4392b",
      "renderPriority" : "NEUTRAL",
      "renditionMap" : { },
      "type" : "component"
    } ],
    "id" : "3f5fd1ac-3ccb-4839-a105-5abfe19af03e",
    "regionName" : "content",
    "type" : "region"
  }, {
    "components" : [ {
      "componentAttributes" : {
        "deleteButtonText" : "Delete",
        "pageSize" : 10,
        "resumeButtonAlign" : "right",
        "resumeButtonLabel" : "Resume",
        "showDeleteButton" : false,
        "showNumberInTitle" : true,
        "showOwnerName" : false,
        "showPauseReason" : true,
        "showPauseStep" : true,
        "showPauseTime" : true,
        "title" : "Paused Flows"
      },
      "componentName" : "forceCommunity:pausedInterviewCard",
      "id" : "4fc4113d-d65c-474c-8664-058b62238525",
      "renderPriority" : "NEUTRAL",
      "renditionMap" : { },
      "type" : "component"
    }, {
      "componentAttributes" : {
        "richTextValue" : "             <p><b style=\"font-size: 16px;\">Quick Links</b></p>             <p><br></p>             <p><a href=\"http://www.salesforce.com/\" target=\"_blank\">Link 1</a></p>             <p><br></p>             <p><a href=\"http://www.salesforce.com/\" target=\"_blank\">Link 2</a></p>             <p><br></p>             <p><a href=\"http://www.salesforce.com/\" target=\"_blank\">Link 3</a></p>             <p><br></p>             <p><a href=\"http://www.salesforce.com/\" target=\"_blank\">Link 4</a></p>         "
      },
      "componentName" : "forceCommunity:richTextInline",
      "id" : "550b6c7d-ab2b-4dd5-af9c-4abe3e2167c0",
      "renderPriority" : "NEUTRAL",
      "renditionMap" : { },
      "type" : "component"
    } ],
    "id" : "f07b4745-3bee-4fea-894e-5eda6a9e5bb9",
    "regionName" : "sidebar",
    "type" : "region"
  }, {
    "id" : "6b135f70-0f05-4158-8608-0686569acd8a",
    "regionName" : "footer",
    "type" : "region"
  }, {
    "components" : [ {
      "componentAttributes" : {
        "customHeadTags" : "",
        "description" : "",
        "title" : "Home"
      },
      "componentName" : "forceCommunity:seoAssistant",
      "id" : "2e199f4e-4579-4fb5-b84a-c346ac85d7a7",
      "renditionMap" : { },
      "type" : "component"
    } ],
    "id" : "e4393232-a7bb-46c2-9de1-618bd098911e",
    "regionName" : "sfdcHiddenRegion",
    "type" : "region"
  } ],
  "themeLayoutType" : "Inner",
  "type" : "view",
  "viewType" : "home"
}